ntcplot/__init__.py
ntcplot/ihm.py
ntcplot/netcdf_functions.py
ntcplot/ntcplot.py
ntcplot/values.py
NtcPlot-0.0.2.dist-info/LICENSE
NtcPlot-0.0.2.dist-info/METADATA
NtcPlot-0.0.2.dist-info/WHEEL
NtcPlot-0.0.2.dist-info/entry_points.txt
NtcPlot-0.0.2.dist-info/top_level.txt
NtcPlot-0.0.2.dist-info/RECORD
