Metadata-Version: 2.1
Name: NtcPlot
Version: 0.0.2
Summary: Package of NtcPlot
Author-email: Alex Papadopoulos <papadopoulos.al@outlook.com>
Project-URL: Homepage, https://pypi.org/project/ntcplot/
Classifier: Programming Language :: Python :: 3
Classifier: License :: OSI Approved :: MIT License
Classifier: Operating System :: OS Independent
Requires-Python: >=3.12
License-File: LICENSE
Requires-Dist: PyQt6 >=6.7.0
Requires-Dist: numpy >=1.26.0
Requires-Dist: netCDF4 >=1.7.0
Requires-Dist: matplotlib >=3.8.0
Requires-Dist: basemap >=1.4.1
